remoteRF/__init__.py
remoteRF/remoterf_cli.py
remoteRF/version.py
remoteRF/common/__init__.py
remoteRF/common/grpc/__init__.py
remoteRF/common/grpc/grpc_pb2.py
remoteRF/common/grpc/grpc_pb2_grpc.py
remoteRF/common/utils/__init__.py
remoteRF/common/utils/ansi_codes.py
remoteRF/common/utils/api_token.py
remoteRF/common/utils/list_string.py
remoteRF/common/utils/process_arg.py
remoteRF/config/__init__.py
remoteRF/config/cert_fetcher.py
remoteRF/config/config.py
remoteRF/core/__init__.py
remoteRF/core/acc_login.py
remoteRF/core/app.py
remoteRF/core/grpc_acc.py
remoteRF/core/grpc_client.py
remoteRF/drivers/__init__.py
remoteRF/drivers/adalm_pluto/__init__.py
remoteRF/drivers/adalm_pluto/pluto_remote.py
remoterf-1.1.2.dist-info/METADATA
remoterf-1.1.2.dist-info/WHEEL
remoterf-1.1.2.dist-info/entry_points.txt
remoterf-1.1.2.dist-info/top_level.txt
remoterf-1.1.2.dist-info/RECORD
