Metadata-Version: 2.4
Name: remoterf
Version: 1.1.2
Summary: A python API to remotely access signal centric hardware. Client-side only! Courtesy of Wireless Lab @ UCLA & Prof. Ian Roberts.
Author: Ethan Ge
Author-email: ethoGalaxy@gmail.com
Classifier: Programming Language :: Python :: 3
Classifier: License :: OSI Approved :: MIT License
Classifier: Operating System :: OS Independent
Requires-Python: >=3.10
Requires-Dist: grpcio==1.71.0
Requires-Dist: protobuf<6.0.0,>=5.0.0
Requires-Dist: numpy
Requires-Dist: prompt_toolkit
Requires-Dist: python-dotenv
Requires-Dist: prompt-toolkit
Dynamic: author
Dynamic: author-email
Dynamic: classifier
Dynamic: description
Dynamic: description-content-type
Dynamic: requires-dist
Dynamic: requires-python
Dynamic: summary
